{
  "name": "python3-pybind11",
  "buildsystem": "simple",
  "build-commands": [
    "pip3 install --verbose --exists-action=i --no-index --find-links=\"file://${PWD}\" --prefix=${FLATPAK_DEST} \"pybind11\" --no-build-isolation"
  ],
  "sources": [
    {
      "type": "file",
      "url": "https://files.pythonhosted.org/packages/26/55/e776489172f576b782e616f58273e1f3de56a91004b0d20504169dd345af/pybind11-2.12.0-py3-none-any.whl",
      "sha256": "df8d60b94f9e714d81013db233393d430ebf9f3551642b82291cf1b14d1afdbd"
    }
  ]
}
